hltv_stats/__init__.py
hltv_stats/match.py
hltv_stats/parser.py
hltv_stats/team.py
hltv_stats/upcoming_matches.py
hltv_stats-0.1.7.dist-info/WHEEL
hltv_stats-0.1.7.dist-info/METADATA
hltv_stats-0.1.7.dist-info/RECORD
